<?xml version="1.0" encoding="utf-8" ?><dwsync><file name="view.php" server="ftp.i-visionsolutions.com" local="3531234176" remote="318763443924101892" Dst="-1" /><file name="details.php" server="ftp.i-visionsolutions.com" local="3533651702" remote="318763443926519412" Dst="-1" /><file name=".DS_Store" server="ftp.i-visionsolutions.com" local="3513444881" remote="318763443907453872" Dst="-1" /><file name="insurances.php" server="ftp.i-visionsolutions.com" local="3513444881" remote="318763443907453872" Dst="-1" /><file name="listview.php" server="ftp.i-visionsolutions.com" local="3513444881" remote="318763443907453872" Dst="-1" /><file name="sponsors.php" server="ftp.i-visionsolutions.com" local="3513444881" remote="318763443907453872" Dst="-1" /><file name="view - Copy.php" server="ftp.i-visionsolutions.com" local="3513444882" remote="318763443907453872" Dst="-1" /><file name="companies_search.php" server="ftp.i-visionsolutions.com" local="3513444881" remote="318763443907453872" Dst="-1" /><file name="_navigation.php" server="ftp.i-visionsolutions.com" local="3533402715" remote="318763443926270412" Dst="-1" /><file name="branches.php" server="ftp.i-visionsolutions.com" local="3534184174" remote="318763443927051852" Dst="-1" /><file name="index.php" server="ftp.i-visionsolutions.com" local="3533405705" remote="318763443926273412" Dst="-1" /><file name="insurance_form.php" server="ftp.i-visionsolutions.com" local="3534255342" remote="318763443927123012" Dst="-1" /><file name="branch_form.php" server="ftp.i-visionsolutions.com" local="3519055753" remote="318763443911919852" Dst="-1" /><file name="directors.php" server="ftp.i-visionsolutions.com" local="3534183739" remote="318763443927051432" Dst="-1" /><file name="branch_details.php" server="ftp.i-visionsolutions.com" local="3518799817" remote="318763443911744892" Dst="-1" /><file name="executive.php" server="ftp.i-visionsolutions.com" local="3534183561" remote="318763443927051252" Dst="-1" /></dwsync>